simulus/__init__.py
simulus/bucket.py
simulus/event.py
simulus/mailbox.py
simulus/process.py
simulus/resource.py
simulus/semaphore.py
simulus/simulator.py
simulus/simulus.py
simulus/store.py
simulus/sync.py
simulus/trap.py
simulus/trappable.py
simulus/utils.py
simulus-1.2.1.dist-info/LICENSE
simulus-1.2.1.dist-info/METADATA
simulus-1.2.1.dist-info/WHEEL
simulus-1.2.1.dist-info/top_level.txt
simulus-1.2.1.dist-info/RECORD
