Metadata-Version: 2.1
Name: simulus
Version: 1.2.1
Summary: A Discrete-Event Simulator in Python
Home-page: http://simulus.readthedocs.io/
Author: Jason Liu
Author-email: jasonxliu2010@gmail.com
License: MIT
Platform: UNKNOWN
Classifier: Development Status :: 3 - Alpha
Classifier: Programming Language :: Python :: 3
Classifier: License :: OSI Approved :: MIT License
Classifier: Operating System :: OS Independent
Requires-Python: >=2.8
